base32_lib/__init__.py
base32_lib/base32.py
base32_lib/version.py
base32_lib-1.0.2.dist-info/AUTHORS.rst
base32_lib-1.0.2.dist-info/LICENSE
base32_lib-1.0.2.dist-info/METADATA
base32_lib-1.0.2.dist-info/WHEEL
base32_lib-1.0.2.dist-info/top_level.txt
base32_lib-1.0.2.dist-info/RECORD
