Metadata-Version: 2.1
Name: base32-lib
Version: 1.0.2
Summary: Small library to generate, encode and decode random base32 strings.
Home-page: https://github.com/inveniosoftware/base32-lib
Author: Invenio Software
Author-email: info@inveniosoftware.org
License: MIT License
Keywords: base32 identifiers
Platform: any
Classifier: Intended Audience :: Developers
Classifier: License :: OSI Approved :: MIT License
Classifier: Operating System :: OS Independent
Classifier: Programming Language :: Python
Classifier: Programming Language :: Python :: 3
Classifier: Programming Language :: Python :: 3.6
Classifier: Programming Language :: Python :: 3.7
Provides-Extra: docs
Provides-Extra: tests
Provides-Extra: all
